CHANGELOG.txt
LICENCE.txt
MANIFEST.in
README.txt
setup.py
hillclimbers/__init__.py
hillclimbers.egg-info/PKG-INFO
hillclimbers.egg-info/SOURCES.txt
hillclimbers.egg-info/dependency_links.txt
hillclimbers.egg-info/requires.txt
hillclimbers.egg-info/top_level.txt