Metadata-Version: 2.1
Name: hillclimbers
Version: 0.1.2
Summary: A module to iteratively blend machine learning model predictions.
Home-page: UNKNOWN
Author: Matt-OP
License: MIT
Keywords: python,data,dataframe,machine learning,predictions,blending,pandas,numpy
Platform: UNKNOWN
Classifier: Development Status :: 5 - Production/Stable
Classifier: Intended Audience :: Developers
Classifier: Programming Language :: Python :: 3
Classifier: Operating System :: Unix
Classifier: Operating System :: MacOS :: MacOS X
Classifier: Operating System :: Microsoft :: Windows
Classifier: License :: OSI Approved :: MIT License
Classifier: Programming Language :: Python :: 3
License-File: LICENCE.txt
